fastapi_starter/__init__.py
fastapi_starter/_version.py
fastapi_starter/cli.py
fastapi_starter/template/.env
fastapi_starter/template/alembic.ini
fastapi_starter/template/main.py
fastapi_starter/template/requirements.txt
fastapi_starter/template/app/__init__.py
fastapi_starter/template/app/dependencies.py
fastapi_starter/template/app/api/__init__.py
fastapi_starter/template/app/api/user.py
fastapi_starter/template/app/auth/__init__.py
fastapi_starter/template/app/auth/jwt_handler.py
fastapi_starter/template/app/auth/password_utils.py
fastapi_starter/template/app/auth/routes.py
fastapi_starter/template/app/core/__init__.py
fastapi_starter/template/app/core/config.py
fastapi_starter/template/app/core/database.py
fastapi_starter/template/app/core/logging_config.py
fastapi_starter/template/app/external_services/__init__.py
fastapi_starter/template/app/external_services/email.py
fastapi_starter/template/app/external_services/notification.py
fastapi_starter/template/app/middleware/exception_logging.py
fastapi_starter/template/app/models/__init__.py
fastapi_starter/template/app/models/base.py
fastapi_starter/template/app/models/user.py
fastapi_starter/template/app/routers/__init__.py
fastapi_starter/template/app/routers/users.py
fastapi_starter/template/app/schemas/__init__.py
fastapi_starter/template/app/schemas/user.py
fastapi_starter/template/app/utils/__init__.py
fastapi_starter/template/app/utils/token.py
fastapi_starter/template/app/utils/validation.py
fastapi_starter/template/migrations/README
fastapi_starter/template/migrations/env.py
fastapi_starter/template/migrations/script.py.mako
fastapi_starter/template/migrations/versions/65827262450c_init_db.py
fastapi_starter/template/migrations/versions/c82632d6b4af_create_user_and_token_table.py
fastapi_starter/template/tests/__init__.py
fastapi_starter/template/tests/conftest.py
fastapi_starter/template/tests/test_auth.py
fastapi_starter/template/tests/test_users.py
fastapi_starter_kit-0.1.17.dist-info/licenses/LICENSE
fastapi_starter_kit-0.1.17.dist-info/METADATA
fastapi_starter_kit-0.1.17.dist-info/WHEEL
fastapi_starter_kit-0.1.17.dist-info/entry_points.txt
fastapi_starter_kit-0.1.17.dist-info/top_level.txt
fastapi_starter_kit-0.1.17.dist-info/RECORD
