Metadata-Version: 2.4
Name: fastapi-starter-kit
Version: 0.1.17
Summary: Starter template for FastAPI projects with JWT authentication and role-based access
Author-email: Jay Jani <jayjani0311@gmail.com>
License: MIT License
Project-URL: Homepage, https://github.com/jay0311-dev/fastapi-starter-kit
Project-URL: Documentation, https://github.com/jay0311-dev/fastapi-starter-kit#readme
Project-URL: Source, https://github.com/jay0311-dev/fastapi-starter-kit
Keywords: fastapi,starter,boilerplate,template,jwt,authentication,authorization,sqlalchemy,alembic,pydantic,api,python
Classifier: Development Status :: 5 - Production/Stable
Classifier: Intended Audience :: Developers
Classifier: Topic :: Software Development :: Libraries :: Application Frameworks
Classifier: Programming Language :: Python :: 3.10
Classifier: Framework :: FastAPI
Classifier: License :: OSI Approved :: MIT License
Classifier: Operating System :: OS Independent
Requires-Python: >=3.10
License-File: LICENSE
Requires-Dist: fastapi>=0.115.0
Requires-Dist: uvicorn>=0.30.0
Requires-Dist: SQLAlchemy>=2.0
Requires-Dist: alembic>=1.13
Requires-Dist: python-jose>=3.3
Requires-Dist: passlib[argon2]>=1.7
Requires-Dist: argon2-cffi>=23.2.0
Requires-Dist: pydantic>=2.8.0
Requires-Dist: pydantic-settings>=2.0.0
Requires-Dist: email-validator
Requires-Dist: python-dotenv
Requires-Dist: click>=8.0.0
Dynamic: license-file
